{
  "passages": [
    {
      "text": "You are at a foot of a cave. You enter. Immediately, you encounter a foot at the road. Which passge do you take?\n[[Go to the left->Left]]\n[[Go to the right->Right]]",
      "links": [
        {
          "name": "Go to the left",
          "link": "Left",
          "pid": "2"
        },
        {
          "name": "Go to the right",
          "link": "Right",
          "pid": "3"
        }
      ],
      "name": "Start",
      "pid": "1",
      "position": {
        "x": "412",
        "y": "189"
      }
    },
    {
      "text": "As you walk, you quickly come afoot to a large gap on the floor. It goes so far down, you can't even seem to see the bottom of it. Looking ahead, you can see an edge of clif leading to some more ground. You think you might be able to jump across, but you are not entireluy sure if you can do it.\nDo you want to go back to where its safe or do you try to jump the gap on the floor?\n[[Go back->Start]]\n[[Try to jump across->Platform]]",
      "links": [
        {
          "name": "Go back",
          "link": "Start",
          "pid": "1"
        },
        {
          "name": "Try to jump across",
          "link": "Platform",
          "pid": "4"
        }
      ],
      "name": "Left",
      "pid": "2",
      "position": {
        "x": "326",
        "y": "337"
      }
    },
    {
      "text": "It doesn't take very long for you to find yourself face-to-face with a wall. It looks as if it was the result of a cave in. Inspecting it a little closer, through its cracks,  you can see what appears to be light! You think you're strong enough to be able to push some of those rocks out of the way to make an opening, but you also imagine that you might hurt your hands in the process of it...\n[[Do you want to go back to the start?->Start]]\n[[Or do you try to make an opening?->Puzzle]]",
      "links": [
        {
          "name": "Do you want to go back to the start?",
          "link": "Start",
          "pid": "1"
        },
        {
          "name": "Or do you try to make an opening?",
          "link": "Puzzle",
          "pid": "7"
        }
      ],
      "name": "Right",
      "pid": "3",
      "position": {
        "x": "532",
        "y": "339"
      }
    },
    {
      "text": "You somehow make it. You see a chest and you open it. There is a sword inside! You decide to take it with you.\nAs you move forward, you come across an abnoramlly large spider. You could try to sneak around it or you could attack it using your newfound sword.\n[[Attack the spider!->Attacked]]\n[[Sneak past->Sneaked]]",
      "links": [
        {
          "name": "Attack the spider!",
          "link": "Attacked",
          "pid": "5"
        },
        {
          "name": "Sneak past",
          "link": "Sneaked",
          "pid": "6"
        }
      ],
      "name": "Platform",
      "pid": "4",
      "position": {
        "x": "326",
        "y": "487"
      }
    },
    {
      "text": "You attack the spider and somehow defeat it! You continue onward unscathed!",
      "name": "Attacked",
      "pid": "5",
      "position": {
        "x": "251",
        "y": "637"
      }
    },
    {
      "text": "Unfortunately, stealth is not one of your strengths, and you accidentally kick a rock a little too hard and alert the spider to your presence. You start running as fast as you can and you can hear the spider start chasing you.",
      "name": "Sneaked",
      "pid": "6",
      "position": {
        "x": "401",
        "y": "637"
      }
    },
    {
      "text": "This is the Puzzle room. You need to complete a puzzle here, but we don't need it for right now.\n[[This is where you go when you complete the puzzle successfully->Lair]]\n[[This is where you go when you fail the puzzle->Death]]",
      "links": [
        {
          "name": "This is where you go when you complete the puzzle successfully",
          "link": "Lair",
          "pid": "8"
        },
        {
          "name": "This is where you go when you fail the puzzle",
          "link": "Death",
          "pid": "9"
        }
      ],
      "name": "Puzzle",
      "pid": "7",
      "position": {
        "x": "532",
        "y": "489"
      }
    },
    {
      "text": "The Lair room",
      "name": "Lair",
      "pid": "8",
      "position": {
        "x": "521",
        "y": "639"
      }
    },
    {
      "text": "The Death Dimension",
      "name": "Death",
      "pid": "9",
      "position": {
        "x": "641",
        "y": "639"
      }
    }
  ],
  "name": "Project 1",
  "startnode": "1",
  "creator": "Twine",
  "creator-version": "2.3.9",
  "ifid": "64DF13AF-40EF-4DCA-9B5B-3901BE364FC9"
}